znumbers/__init__.py
znumbers/core.py
znumbers-0.2.1.dist-info/licenses/LICENSE.md
znumbers-0.2.1.dist-info/METADATA
znumbers-0.2.1.dist-info/WHEEL
znumbers-0.2.1.dist-info/top_level.txt
znumbers-0.2.1.dist-info/RECORD
