Metadata-Version: 2.4
Name: znumbers
Version: 0.2.1
Summary: Z-numbers arithmetic library (Lotfi Zadeh’s Z-numbers, with 4 basic operations)
Author-email: Dilmurod Yusupov Tasbaltayevich <cazinoroyal1987@gmail.com>
License-File: LICENSE.md
Requires-Dist: numpy
Requires-Dist: scipy
Dynamic: license-file
